[
  {
    "id": 1,
    "name": "攻击1",
    "ani": "Combo1",
    "self_effect": null,
    "target_effect": null,
    "dis": 1,
    "behavior_buff": null,
    "move_buff": null,
    "hurt_buff": null,
    "constrol_buff": null
  },
  {
    "id": 2,
    "name": "攻击2",
    "ani": "Combo1_1",
    "self_effect": null,
    "target_effect": null,
    "dis": 1,
    "behavior_buff": null,
    "move_buff": null,
    "hurt_buff": null,
    "constrol_buff": null
  },
  {
    "id": 3,
    "name": "攻击3",
    "ani": "Combo1_2",
    "self_effect": null,
    "target_effect": null,
    "dis": 5,
    "behavior_buff": null,
    "move_buff": null,
    "hurt_buff": null,
    "constrol_buff": null
  },
  {
    "id": 4,
    "name": "攻击4",
    "ani": "Combo1_3",
    "self_effect": null,
    "target_effect": null,
    "dis": 5,
    "behavior_buff": null,
    "move_buff": null,
    "hurt_buff": null,
    "constrol_buff": null
  }
]